makemakef/__init__.py
makemakef/main.py
makemakef-0.2.12.dist-info/LICENSE
makemakef-0.2.12.dist-info/METADATA
makemakef-0.2.12.dist-info/WHEEL
makemakef-0.2.12.dist-info/entry_points.txt
makemakef-0.2.12.dist-info/top_level.txt
makemakef-0.2.12.dist-info/RECORD
